hw1/hw1p2.sv
/* Module for EE/CSE371 Homework 1 Problem 2.
 * An arbitrary Mealy FSM.
 */
module hw1p2 (
	input logic clk
	,input logic reset
	,input logic in
	,output logic out
);
	logic [2:0] ps, ns;
	//dermining the next state based on input and current state
	always_comb begin 
		case (ps)
			3'b000:begin 
				if(in) begin
					ns = 3'b100;
					out = 1'b1;
				end
				else begin
					ns = 3'b011;
					out = 1'b0;
				end
			end
			3'b001:begin
				if (in)begin
					ns = 3'b100;
					out = 1'b1;
				end
				else begin
					ns = 3'b001;
					out = 1'b0;
				end
			end
			3'b010:begin
				if (in) begin
					ns = 3'b000;
					out = 1'b1;
				end
				else begin
					ns = 3'b010;
					out = 1'b0;
				end
			end
			3'b011:begin
				if (in)begin 
					ns = 3'b010;
					out = 1'b1;
				end
				else begin
					ns = 3'b001;
					out = 1'b0;
				end
			end
			3'b100:begin
				if (in)begin
					ns = 3'b011;
					out = 1'b0;
				end
				else begin
					ns = 3'b010;
					out = 1'b0;
				end
			end
			default: begin 
					ns = 3'bxxx;
					out = 1'bx;
			end
					
		endcase
		
	end

	// update the current state on the clock edge
	always_ff @(posedge clk) begin
		if (reset) 
			ps <= 3'b000;
		else 
			ps <= ns;
	end	

	// for you to implement

endmodule  // hw1p2

hw1/hw1p2_tb.sv
/* Testbench for Homework 1 Problem 2 */
module hw1p2_tb();
	logic clk, reset, in, out;
	hw1p2 dut(clk, reset, in, out);

	parameter CLOCK_PERIOD=100;
   initial
	 clk = 0;
   always
	 #(CLOCK_PERIOD/2)  clk <= ~clk;

	initial begin
    reset = 1; in = 0; @(posedge clk);
	reset = 0; @(posedge clk);
    in = 0; @(posedge clk);
    in = 0; @(posedge clk);
    in = 0; @(posedge clk);
    in = 1; @(posedge clk);
    in = 0; @(posedge clk);
    in = 1; @(posedge clk);
    $stop;
  end


	// this is just for verilator to give me a VCD :)
	// initial begin
	// 	$dumpfile("dump2.vcd");   
	// 	$dumpvars();
	// end
	
endmodule  // hw1p2_tb

hw1/obj_dir/dump2.vcd
$version Generated by VerilatedVcd $end
$timescale 1ps $end
 $scope module $rootio $end
 $upscope $end
 $scope module hw1p2_tb $end
  $var wire 1 # clk $end
  $var wire 1 $ reset $end
  $var wire 1 % in $end
  $var wire 1 & out $end
  $var wire 32 ) CLOCK_PERIOD [31:0] $end
  $scope module dut $end
   $var wire 1 # clk $end
   $var wire 1 $ reset $end
   $var wire 1 % in $end
   $var wire 1 & out $end
   $var wire 3 ' ps [2:0] $end
   $var wire 3 ( ns [2:0] $end
  $upscope $end
 $upscope $end
$enddefinitions $end


#0
0#
1$
0%
0&
b000 '
b011 (
b00000000000000000000000001100100 )
#50
1#
0$
b011 '
b001 (
#100
0#
#150
1#
1%
1&
b010 '
b000 (
#200
0#
#250
1#
0%
0&
b010 (
#300
0#
#350
1#
1%
1&
b000 '
b100 (
#400
0#
#450
1#
0%
0&
b011 '
b001 (
#500
0#
#550
1#
1%
1&
b010 '
b000 (
#600
0#
#650
1#
0%
0&
b010 (
